neurocaps/__init__.py
neurocaps/_utils/__init__.py
neurocaps/_utils/_check_kwargs.py
neurocaps/_utils/_check_parcel_approach.py
neurocaps/_utils/_pickle_to_dict.py
neurocaps/_utils/_cap_internals/__init__.py
neurocaps/_utils/_cap_internals/_cap2statmap.py
neurocaps/_utils/_cap_internals/_capgetter.py
neurocaps/_utils/_cap_internals/_run_kmeans.py
neurocaps/_utils/_timeseriesextractor_internals/__init__.py
neurocaps/_utils/_timeseriesextractor_internals/_check_confound_names.py
neurocaps/_utils/_timeseriesextractor_internals/_extract_timeseries.py
neurocaps/_utils/_timeseriesextractor_internals/_timeseriesextractorgetter.py
neurocaps/analysis/__init__.py
neurocaps/analysis/cap.py
neurocaps/analysis/merge.py
neurocaps/analysis/standardize.py
neurocaps/extraction/__init__.py
neurocaps/extraction/timeseriesextractor.py
neurocaps-1.0.0.post4.dist-info/LICENSE.md
neurocaps-1.0.0.post4.dist-info/METADATA
neurocaps-1.0.0.post4.dist-info/WHEEL
neurocaps-1.0.0.post4.dist-info/top_level.txt
neurocaps-1.0.0.post4.dist-info/RECORD
