Metadata-Version: 2.1
Name: neurocaps
Version: 1.0.0.post4
Summary: Co-activation Patterns (CAPs) Python package
Author-email: Donisha Smith <donishasmith@outlook.com>
License: MIT License
Project-URL: Homepage, https://neurocaps.readthedocs.io/en/latest/
Project-URL: Github, https://github.com/donishadsmith/neurocaps
Project-URL: Issues, https://github.com/donishadsmith/neurocaps/issues
Project-URL: Changelog, https://neurocaps.readthedocs.io/en/latest/changelog.html
Keywords: python,Co-Activation Patterns,CAPs,neuroimaging,fmri,dfc,dynamic functional connectivity,fMRIPrep
Classifier: Intended Audience :: Education
Classifier: Intended Audience :: Science/Research
Classifier: Topic :: Scientific/Engineering
Classifier: License :: OSI Approved :: MIT License
Classifier: Programming Language :: Python :: 3.9
Classifier: Programming Language :: Python :: 3.10
Classifier: Programming Language :: Python :: 3.11
Classifier: Programming Language :: Python :: 3.12
Classifier: Operating System :: MacOS :: MacOS X
Classifier: Operating System :: POSIX :: Linux
Classifier: Operating System :: Microsoft :: Windows :: Windows 11
Classifier: Development Status :: 4 - Beta
Requires-Python: >=3.9.0
License-File: LICENSE.md
Requires-Dist: numpy >=1.22.0
Requires-Dist: pandas >=2.0.0
Requires-Dist: joblib >=1.3.0
Requires-Dist: matplotlib >=3.6.0
Requires-Dist: seaborn >=0.11.0
Requires-Dist: kneed
Requires-Dist: nibabel >=3.2.0
Requires-Dist: nilearn !=0.10.3,>=0.10.1
Requires-Dist: scikit-learn >=1.4.0
Requires-Dist: surfplot
Requires-Dist: neuromaps
Requires-Dist: plotly
Requires-Dist: pybids >=0.16.2 ; platform_system != "Windows"
Requires-Dist: kaleido ; platform_system != "Windows"
Requires-Dist: kaleido ==0.1.0.post1 ; platform_system == "Windows"
